{
  "sample_id": "0653",
  "replace_count": 5,
  "changed_count": 5,
  "changed_fields": [
    {
      "field": "entity",
      "old": "single",
      "new": "double"
    },
    {
      "field": "operation",
      "old": "spiraling",
      "new": "peeling"
    },
    {
      "field": "direction",
      "old": "horizontal",
      "new": "radial"
    },
    {
      "field": "volume",
      "old": "disk",
      "new": "vortex"
    },
    {
      "field": "affect",
      "old": "concave",
      "new": "vortical"
    }
  ]
}
